experiments/__init__.py
experiments/config.py
experiments/data.py
experiments/experiments.py
experiments/metrics.py
experiments/models.py
experiments/run.py
experiments/train.py
sgu_mlp/__init__.py
sgu_mlp/models.py
sgu_mlp-0.1.1.dist-info/LICENSE
sgu_mlp-0.1.1.dist-info/METADATA
sgu_mlp-0.1.1.dist-info/WHEEL
sgu_mlp-0.1.1.dist-info/entry_points.txt
sgu_mlp-0.1.1.dist-info/RECORD
