Metadata-Version: 2.3
Name: sgu-mlp
Version: 0.1.1
Summary: Implementation of the SGU-MLP Architecture (mostly) as described in the paper "Spatial Gated Multi-Layer Perceptron for Land Use and Land Cover Mapping".
Author: Marius Hamacher
Author-email: marius.hamacher@outlook.de
Requires-Python: >=3.10,<4.0
Classifier: Development Status :: 3 - Alpha
Classifier: Environment :: Console
Classifier: Environment :: GPU
Classifier: Environment :: GPU :: NVIDIA CUDA
Classifier: Intended Audience :: Developers
Classifier: Intended Audience :: Information Technology
Classifier: Intended Audience :: Science/Research
Classifier: License :: OSI Approved :: MIT License
Classifier: Natural Language :: English
Classifier: Operating System :: OS Independent
Classifier: Programming Language :: Python :: 3
Classifier: Programming Language :: Python :: 3.10
Classifier: Programming Language :: Python :: 3.11
Classifier: Programming Language :: Python :: 3.12
Classifier: Programming Language :: Python :: 3.13
Classifier: Topic :: Scientific/Engineering :: Artificial Intelligence
Classifier: Topic :: Scientific/Engineering :: Image Processing
Classifier: Topic :: Scientific/Engineering :: Image Recognition
Classifier: Topic :: Software Development :: Libraries :: Python Modules
Requires-Dist: numpy (>=2.2.1,<3.0.0)
Requires-Dist: torch (>=2.5.1,<3.0.0)
